<?xml version="1.0" encoding="UTF-8" ?>
<!DOCTYPE mapper PUBLIC "-//mybatis.org//DTD Mapper 3.0//EN" "http://mybatis.org/dtd/mybatis-3-mapper.dtd" >
<mapper namespace="com.gsccs.cms.core.dao.RoleWxappMapper" >
  <resultMap id="BaseResultMap" type="com.gsccs.cms.core.model.RoleWxapp" >
    <id column="id" property="id" jdbcType="VARCHAR" />
    <result column="roleid" property="roleid" jdbcType="VARCHAR" />
    <result column="wxappid" property="wxappid" jdbcType="VARCHAR" />
  </resultMap>
  <sql id="Example_Where_Clause" >
    <where >
      <foreach collection="oredCriteria" item="criteria" separator="or" >
        <if test="criteria.valid" >
          <trim prefix="(" suffix=")" prefixOverrides="and" >
            <foreach collection="criteria.criteria" item="criterion" >
              <choose >
                <when test="criterion.noValue" >
                  and ${criterion.condition}
                </when>
                <when test="criterion.singleValue" >
                  and ${criterion.condition} #{criterion.value}
                </when>
                <when test="criterion.betweenValue" >
                  and ${criterion.condition} #{criterion.value} and #{criterion.secondValue}
                </when>
                <when test="criterion.listValue" >
                  and ${criterion.condition}
                  <foreach collection="criterion.value" item="listItem" open="(" close=")" separator="," >
                    #{listItem}
                  </foreach>
                </when>
              </choose>
            </foreach>
          </trim>
        </if>
      </foreach>
    </where>
  </sql>
  <sql id="Update_By_Example_Where_Clause" >
    <!--
      WARNING - @mbggenerated
      This element is automatically generated by MyBatis Generator, do not modify.
      This element was generated on Tue Oct 16 21:25:57 CST 2012.
    -->
    <where >
      <foreach collection="example.oredCriteria" item="criteria" separator="or" >
        <if test="criteria.valid" >
          <trim prefix="(" suffix=")" prefixOverrides="and" >
            <foreach collection="criteria.criteria" item="criterion" >
              <choose >
                <when test="criterion.noValue" >
                  and ${criterion.condition}
                </when>
                <when test="criterion.singleValue" >
                  and ${criterion.condition} #{criterion.value}
                </when>
                <when test="criterion.betweenValue" >
                  and ${criterion.condition} #{criterion.value} and #{criterion.secondValue}
                </when>
                <when test="criterion.listValue" >
                  and ${criterion.condition}
                  <foreach collection="criterion.value" item="listItem" open="(" close=")" separator="," >
                    #{listItem}
                  </foreach>
                </when>
              </choose>
            </foreach>
          </trim>
        </if>
      </foreach>
    </where>
  </sql>
  <sql id="Base_Column_List" >
    <!--
      WARNING - @mbggenerated
      This element is automatically generated by MyBatis Generator, do not modify.
      This element was generated on Tue Oct 16 21:25:57 CST 2012.
    -->
    id, roleid, wxappid
  </sql>
  <select id="selectByExample" resultMap="BaseResultMap" parameterType="com.gsccs.cms.core.model.RoleWxappExample" >
    select
    <if test="distinct" >
      distinct
    </if>
    <include refid="Base_Column_List" />
    from cms_role_wxapp
    <if test="_parameter != null" >
      <include refid="Example_Where_Clause" />
    </if>
    <if test="orderByClause != null" >
      order by ${orderByClause}
    </if>
  </select>
  <select id="selectByPrimaryKey" resultMap="BaseResultMap" parameterType="java.lang.String" >
    select 
    <include refid="Base_Column_List" />
    from cms_role_wxapp
    where id = #{id,jdbcType=VARCHAR}
  </select>
  <delete id="deleteByPrimaryKey" parameterType="java.lang.String" >
    delete from cms_role_wxapp
    where id = #{id,jdbcType=VARCHAR}
  </delete>
  <delete id="deleteByExample" parameterType="com.gsccs.cms.core.model.RoleWxappExample" >
    <!--
      WARNING - @mbggenerated
      This element is automatically generated by MyBatis Generator, do not modify.
      This element was generated on Tue Oct 16 21:25:57 CST 2012.
    -->
    delete from cms_role_wxapp
    <if test="_parameter != null" >
      <include refid="Example_Where_Clause" />
    </if>
  </delete>
  <insert id="insert" parameterType="com.gsccs.cms.core.model.RoleWxapp" >
    <!--
      WARNING - @mbggenerated
      This element is automatically generated by MyBatis Generator, do not modify.
      This element was generated on Tue Oct 16 21:25:57 CST 2012.
    -->
    insert into cms_role_wxapp (id, roleid, wxappid
      )
    values (#{id,jdbcType=VARCHAR}, #{roleid,jdbcType=VARCHAR}, #{wxappid,jdbcType=VARCHAR}
      )
  </insert>
  <insert id="insertSelective" parameterType="com.gsccs.cms.core.model.RoleWxapp" >
    <!--
      WARNING - @mbggenerated
      This element is automatically generated by MyBatis Generator, do not modify.
      This element was generated on Tue Oct 16 21:25:57 CST 2012.
    -->
    insert into cms_role_wxapp
    <trim prefix="(" suffix=")" suffixOverrides="," >
      <if test="id != null" >
        id,
      </if>
      <if test="roleid != null" >
        roleid,
      </if>
      <if test="wxappid != null" >
        wxappid,
      </if>
    </trim>
    <trim prefix="values (" suffix=")" suffixOverrides="," >
      <if test="id != null" >
        #{id,jdbcType=VARCHAR},
      </if>
      <if test="roleid != null" >
        #{roleid,jdbcType=VARCHAR},
      </if>
      <if test="wxappid != null" >
        #{wxappid,jdbcType=VARCHAR},
      </if>
    </trim>
  </insert>
  <select id="countByExample" parameterType="com.gsccs.cms.core.model.RoleWxappExample" resultType="java.lang.Integer" >
    <!--
      WARNING - @mbggenerated
      This element is automatically generated by MyBatis Generator, do not modify.
      This element was generated on Tue Oct 16 21:25:57 CST 2012.
    -->
    select count(*) from cms_role_wxapp
    <if test="_parameter != null" >
      <include refid="Example_Where_Clause" />
    </if>
  </select>
  <update id="updateByExampleSelective" parameterType="map" >
    <!--
      WARNING - @mbggenerated
      This element is automatically generated by MyBatis Generator, do not modify.
      This element was generated on Tue Oct 16 21:25:57 CST 2012.
    -->
    update cms_role_wxapp
    <set >
      <if test="record.id != null" >
        id = #{record.id,jdbcType=VARCHAR},
      </if>
      <if test="record.roleid != null" >
        roleid = #{record.roleid,jdbcType=VARCHAR},
      </if>
      <if test="record.wxappid != null" >
        wxappid = #{record.wxappid,jdbcType=VARCHAR},
      </if>
    </set>
    <if test="_parameter != null" >
      <include refid="Update_By_Example_Where_Clause" />
    </if>
  </update>
  <update id="updateByExample" parameterType="map" >
    <!--
      WARNING - @mbggenerated
      This element is automatically generated by MyBatis Generator, do not modify.
      This element was generated on Tue Oct 16 21:25:57 CST 2012.
    -->
    update cms_role_wxapp
    set id = #{record.id,jdbcType=VARCHAR},
      roleid = #{record.roleid,jdbcType=VARCHAR},
      wxappid = #{record.wxappid,jdbcType=VARCHAR}
    <if test="_parameter != null" >
      <include refid="Update_By_Example_Where_Clause" />
    </if>
  </update>
  <update id="updateByPrimaryKeySelective" parameterType="com.gsccs.cms.core.model.RoleWxapp" >
    update cms_role_wxapp
    <set >
      <if test="roleid != null" >
        roleid = #{roleid,jdbcType=VARCHAR},
      </if>
      <if test="wxappid != null" >
        wxappid = #{wxappid,jdbcType=VARCHAR},
      </if>
    </set>
    where id = #{id,jdbcType=VARCHAR}
  </update>
  <update id="updateByPrimaryKey" parameterType="com.gsccs.cms.core.model.RoleWxapp" >
    update cms_role_wxapp
    set roleid = #{roleid,jdbcType=VARCHAR},
      wxappid = #{wxappid,jdbcType=VARCHAR}
    where id = #{id,jdbcType=VARCHAR}
  </update>
  
  <sql id="Example_Clause">
      <foreach collection="oredCriteria" item="criteria" separator="or">
        <if test="criteria.valid">
          <trim >
            <foreach collection="criteria.criteria" item="criterion">
              <choose>
                <when test="criterion.noValue">
                  and ${criterion.condition}
                </when>
                <when test="criterion.singleValue">
                  and ${criterion.condition} #{criterion.value}
                </when>
                <when test="criterion.betweenValue">
                  and ${criterion.condition} #{criterion.value} and #{criterion.secondValue}
                </when>
                <when test="criterion.listValue">
                  and ${criterion.condition}
                  <foreach close=")" collection="criterion.value" item="listItem" open="(" separator=",">
                    #{listItem}
                  </foreach>
                </when>
              </choose>
            </foreach>
          </trim>
        </if>
      </foreach>
  </sql>
</mapper>